{
  "bonuses": {
    "WORN": {},
    "HELD": {}
  },
  "nbt_bonuses": {
    "WORN": [],
    "HELD": []
  },
  "salvage": {},
  "vein_data": {
    "chargeCap": 20,
    "chargeRate": 0.08
  },
  "nbt_xp_values": {
    "TOOL_BREAKING": [],
    "DEAL_DAMAGE": [],
    "ENCHANT": [],
    "CONSUME": [],
    "CRAFT": [],
    "ACTIVATE_ITEM": [],
    "RECEIVED_AS_TRADE": [],
    "ANVIL_REPAIR": [],
    "FISH": [],
    "BREW": [],
    "GIVEN_AS_TRADE": [],
    "BLOCK_PLACE": [],
    "SMELT": []
  },
  "damage_type_xp": {
    "RECEIVE_DAMAGE": {},
    "DEAL_DAMAGE": {}
  },
  "nbt_damage_type_xp": {
    "RECEIVE_DAMAGE": {},
    "DEAL_DAMAGE": {}
  },
  "nbt_requirements": {
    "TOOL": [],
    "WEAPON": [],
    "PLACE": [],
    "BREAK": [],
    "USE_ENCHANTMENT": [],
    "WEAR": [],
    "INTERACT": [],
    "USE": []
  },
  "negative_effect": {},
  "xp_values": {
    "TOOL_BREAKING": {
      "farming": 202.0
    },
    "DEAL_DAMAGE": {},
    "ENCHANT": {
      "enchanting": 50
    },
    "CONSUME": {},
    "CRAFT": {
      "farming": 2020
    },
    "ACTIVATE_ITEM": {},
    "RECEIVED_AS_TRADE": {},
    "ANVIL_REPAIR": {
      "smithing": 15000
    },
    "FISH": {},
    "BREW": {},
    "GIVEN_AS_TRADE": {},
    "BLOCK_PLACE": {},
    "SMELT": {}
  },
  "override": true,
  "isTagFor": [],
  "requirements": {
    "TOOL": {
      "smithing": 50,
      "farming": 400
    },
    "PLACE": {
      "farming": 400
    },
    "BREAK": {
      "farming": 400
    },
    "USE_ENCHANTMENT": {},
    "WEAR": {
      "farming": 200
    },
    "INTERACT": {},
    "USE": {
      "smithing": 50,
      "farming": 400
    }
  }
}
